{"name":"Meetingviewer","tagline":"","body":"<h1>Meeting Viewer App</h1>\r\nThis simple PHP + JQuery app uses the Pusher Client Libraries to get the real-time updates on a Meeting/Event.\r\n\r\n<h2>Deploying to Heroku</h2>\r\n* git clone git@github.com:logontokartik/MeetingViewer.git\r\n* heroku apps:create\r\n* git push heroku master\r\n* heroku open\r\n\r\n<h2>Configurartion</h2>\r\nMake sure you add the Application Key from Pusher to connect to your account\r\n* heroku config:add app_key=<YOUR PUSHER APP KEY> \r\n\r\n<TODO>\r\nFor now this application is using the Channel Names, and Event Names hardcoded in the List ID's and is limited only to 3 meetings that are pre-defined. \r\nNeed to figure out a way to make the process automated where the Meetings are pulled from Salesforce dynamically. making them publicly available.\t\r\n","google":"","note":"Don't delete this file! It's used internally to help with page regeneration."}